somata/__init__.py
somata/basic_models/__init__.py
somata/basic_models/arn.py
somata/basic_models/gen.py
somata/basic_models/osc.py
somata/basic_models/ssm.py
somata/exact_inference/__init__.py
somata/exact_inference/dp_func.py
somata/exact_inference/em.py
somata/multitaper/__init__.py
somata/multitaper/fast_psd_multitaper.py
somata/multitaper/multitaper_spectrogram_python.py
somata/oscillator_search/__init__.py
somata/oscillator_search/decomp_osc.py
somata/oscillator_search/helper_functions.py
somata/oscillator_search/iter_osc.py
somata/pac/__init__.py
somata/pac/decimate.py
somata/pac/pac_model.py
somata/pac/stan/pac.stan
somata/pac/stan/sigmoid.stan
somata/source_loc/__init__.py
somata/source_loc/dmap_em.py
somata/source_loc/source_loc_utils.py
somata/switching/__init__.py
somata/switching/traditional.py
somata/switching/vb.py
somata/utils/__init__.py
somata/utils/helper_functions.py
somata/utils/version.py
somata-0.5.6.dist-info/LICENSE
somata-0.5.6.dist-info/METADATA
somata-0.5.6.dist-info/WHEEL
somata-0.5.6.dist-info/top_level.txt
somata-0.5.6.dist-info/RECORD
