Metadata-Version: 2.1
Name: somata
Version: 0.5.6
Summary: State-space Oscillator Modeling And Time-series Analysis
Author-email: Mingjian He <mh1@stanford.edu>
License: BSD 3-Clause Clear License
Project-URL: Homepage, https://github.com/mh105/somata
Project-URL: Documentation, https://github.com/mh105/somata/blob/main/README.md
Project-URL: Repository, https://github.com/mh105/somata
Project-URL: Issues, https://github.com/mh105/somata/issues
Project-URL: Changelog, https://github.com/mh105/somata/blob/main/RELEASE.md
Keywords: state-space,oscillator,time-series
Classifier: Development Status :: 5 - Production/Stable
Classifier: Intended Audience :: Developers
Classifier: Intended Audience :: Science/Research
Classifier: License :: OSI Approved :: BSD License
Classifier: Operating System :: OS Independent
Classifier: Programming Language :: Python :: 3
Classifier: Programming Language :: Python :: 3 :: Only
Classifier: Topic :: Utilities
Classifier: Topic :: Scientific/Engineering :: Mathematics
Classifier: Topic :: Scientific/Engineering :: Information Analysis
Requires-Python: >=3.8
License-File: LICENSE
Requires-Dist: cmdstanpy
Requires-Dist: codetiming
Requires-Dist: colorcet
Requires-Dist: joblib
Requires-Dist: kneed
Requires-Dist: matplotlib
Requires-Dist: mne
Requires-Dist: numpy
Requires-Dist: scipy
Requires-Dist: spectrum
Requires-Dist: statsmodels
Requires-Dist: tqdm
Requires-Dist: torch
